src/design/gray.sv
module gray(input logic [3:0] s,
            output logic b3, b2, b1, b0);

    
    assign b3 = s[3];
    assign b2 = s[2]^b3;
    assign b1 = s[1]^b2;
    assign b0 = s[0]^b1;

endmodule

src/design/bcd.sv
module bcd(input logic [3:0] s,
            output logic [7:0] w);

    
    logic a, b, c, d;
    logic [7:0] y;
    

    gray conv(s[3], s[2], s[1], s[0], a, b, c, d);

    assign y[7:5] = 0;
    assign y[4] =  a & (b | c); 
    assign y[3] = a & ~b & ~c;
    assign y[2] = b & (~a | c);
    assign y[1] =  ~a & c | a & b & ~c;
    assign y[0] = d;


    assign w = {y[7:0]};

endmodule

src/design/segm.sv
module segm(input logic [3:0] s, 
            input logic bot,
            output logic a, b, c, d, e, f, g, an0, an1); // inputs 4 bits iniciales y s boton de cambio (dec/uni)

    assign an0 = 0;
    assign an1 = 0;
 
    logic [7:0] y;  //defino a y que va a pasar por el modulo del bcd
    logic [3:0] bitselec; //defino a la variable que elige los 4 bits de decenas o unidades

    bcd disp(s[3:0], y[7:0]);
    

    assign bitselec = bot ? y[3:0] : y[7:4];  //mux para asignar a bitselec decenas o unidades


    logic a1, b1, c1, d1;       // a partir de aqui logica booleana para cada salida del 7 segm
    assign {a1, b1, c1, d1} = bitselec;



    assign a = ~a1 & ~b1 & ~c1 & d1 | ~a1 & b1 & ~c1 & ~d1 | a1 & b1 & c1 & ~d1 | a1 & ~b1 & c1 & d1;

    assign b = (~a1 & ~b1 & d1) | (~a1 & c1 & d1) | (a1 & ~b1 & ~c1) | (a1 & b1 & ~d1);

    assign c = (~a1 & ~b1 & ~c1 & d1) | (~a1 & b1 & ~c1) | (a1 & ~b1 & ~d1) | (a1 & b1 & c1);

    assign d = (~a1 & ~b1 & ~c1 & d1) | (~a1 & ~b1 & c1 & ~d1) | (~a1 & b1 & ~c1) | (a1 & ~b1 & ~d1);

    assign e = (~a1 & ~b1 & ~c1) | (~a1 & b1 & c1 & d1) | (a1 & ~b1 & d1) | (a1 & b1 & ~c1 & ~d1);

    assign f = ~a1 & ~b1 & d1 | ~a1 & ~b1 & c1 | ~a1 & c1 & d1 | a1 & b1 & ~c1 | ~b1 & c1 & d1;

    assign g = ~a1 & ~b1 & ~c1 | ~a1 & b1 & c1 & d1 | a1 & ~b1 & c1;

endmodule

src/sim/segm_tb.sv
module segm_tb();
    
    logic [3:0] s;
    logic bot;
    logic a, b, c, d, e, f, g;
    logic an0, an1;

    segm dut(.s(s), .bot(bot), .a(a), .b(b), .c(c), .d(d), .e(e), .f(f), .g(g), .an0(an0), .an1(an1));

    initial begin
    
        //Prueba 0
        bot = 1; //Muestra unidades
        s = 4'b0000;  #10; //Gray: 0, decenas:0 , unidades: 0
        //Prueba 1
        bot = 1; //Muestra unidades
        s = 4'b0001; #10; //Gray: 1, decenas:0 , unidades: 1
        //Prueba 2
        bot = 1; //Muestra unidades
        s = 4'b0011; #10; //Gray: 2, decenas:0 , unidades: 2
        //Prueba 3
        bot = 1; //Muestra unidades
        s = 4'b0010; #10; //Gray: 3, decenas:0 , unidades: 3
        //Prueba 4
        bot = 1; //Muestra unidades
        s = 4'b0110; #10; //Gray: 4, decenas:0 , unidades: 4
        //Prueba 5
        bot = 1; //Muestra unidades
        s = 4'b0111; #10; //Gray: 5, decenas:0 , unidades: 5
        //Prueba 6
        bot = 1; //Muestra unidades
        s = 4'b0101; #10; //Gray: 6, decenas:0 , unidades: 6
        //Prueba 7
        bot = 1; //Muestra unidades
        s = 4'b0100; #10; //Gray: 7, decenas:0 , unidades: 7
        //Prueba 8
        bot = 1; //Muestra unidades
        s = 4'b1100; #10; //Gray: 8, decenas:0 , unidades: 8
        //Prueba 9
        bot = 1; //Muestra unidades
        s = 4'b1101; #10; //Gray: 9, decenas:0 , unidades: 9
        //Prueba 10
        bot = 1; //Muestra unidades
        s = 4'b1111; #10; //Gray: 10, decenas:1 , unidades: 0
        //Prueba 11
        bot = 1; //Muestra unidades
        s = 4'b1110; #10; //Gray: 11, decenas:1 , unidades: 1
        //Prueba 12
        bot = 1; //Muestra unidades
        s = 4'b1010; #10; //Gray: 12, decenas:1 , unidades: 2
        //Prueba 13
        bot = 1; //Muestra unidades
        s = 4'b1011; #10; //Gray: 13, decenas:1 , unidades: 3
        //Prueba 14
        bot = 1; //Muestra unidades
        s = 4'b1001; #10; //Gray: 14, decenas:1 , unidades: 4
        //Prueba 15
        bot = 1; //Muestra unidades
        s = 4'b1000; //Gray: 15, decenas:1 , unidades: 5

    end

    initial begin
        $display("Empezando simulacion");

        #160;

        $display("Finalizando simulacion");
        $finish;
    end

    initial begin
        $dumpfile("segm_tb.vcd");
        $dumpvars(0,segm_tb);

    end


endmodule

src/build/segm_tb.vcd
$date
	Mon Aug 26 19:20:07 2024
$end
$version
	Icarus Verilog
$end
$timescale
	1s
$end
$scope module segm_tb $end
$var wire 1 ! an0 $end
$var wire 1 " an1 $end
$var wire 1 # g $end
$var wire 1 $ f $end
$var wire 1 % e $end
$var wire 1 & d $end
$var wire 1 ' c $end
$var wire 1 ( b $end
$var wire 1 ) a $end
$var reg 1 * bot $end
$var reg 4 + s [3:0] $end
$scope module dut $end
$var wire 1 ) a $end
$var wire 1 ! an0 $end
$var wire 1 " an1 $end
$var wire 1 ( b $end
$var wire 1 * bot $end
$var wire 1 ' c $end
$var wire 1 & d $end
$var wire 1 % e $end
$var wire 1 $ f $end
$var wire 1 # g $end
$var wire 4 , s [3:0] $end
$var wire 8 - y [7:0] $end
$var wire 1 . d1 $end
$var wire 1 / c1 $end
$var wire 4 0 bitselec [3:0] $end
$var wire 1 1 b1 $end
$var wire 1 2 a1 $end
$scope module disp $end
$var wire 4 3 s [3:0] $end
$var wire 8 4 y [7:0] $end
$var wire 8 5 w [7:0] $end
$var wire 1 6 d $end
$var wire 1 7 c $end
$var wire 1 8 b $end
$var wire 1 9 a $end
$scope module conv $end
$var wire 1 6 b0 $end
$var wire 1 7 b1 $end
$var wire 1 8 b2 $end
$var wire 4 : s [3:0] $end
$var wire 1 9 b3 $end
$upscope $end
$upscope $end
$upscope $end
$upscope $end
$enddefinitions $end
$comment Show the parameter values. $end
$dumpall
$end
#0
$dumpvars
b0 :
09
08
07
06
b0 5
b0 4
b0 3
02
01
b0 0
0/
0.
b0 -
b0 ,
b0 +
1*
0)
0(
0'
0&
1%
0$
1#
0"
0!
$end
#10
1$
1&
1'
1(
1)
1.
b1 0
b1 -
b1 5
b1 4
16
b1 +
b1 ,
b1 3
b1 :
#20
0%
0#
1&
0'
0(
0)
1/
0.
b10 0
b10 -
b10 5
b10 4
06
17
b11 +
b11 ,
b11 3
b11 :
#30
0&
1(
1.
b11 0
b11 -
b11 5
b11 4
16
b10 +
b10 ,
b10 3
b10 :
#40
1)
1'
1&
0$
0(
0/
0.
11
b100 0
06
07
b100 -
b100 5
b100 4
18
b110 +
b110 ,
b110 3
b110 :
#50
0)
1.
b101 0
b101 -
b101 5
b101 4
16
b111 +
b111 ,
b111 3
b111 :
#60
0'
0)
0&
1/
0.
b110 0
b110 -
b110 5
b110 4
06
17
b101 +
b101 ,
b101 3
b101 :
#70
1$
1%
1(
1#
1.
b111 0
b111 -
b111 5
b111 4
16
b100 +
b100 ,
b100 3
b100 :
#80
1'
0$
0%
1&
0#
12
0.
01
0/
b1000 0
06
07
08
b1000 -
b1000 5
b1000 4
19
b1100 +
b1100 ,
b1100 3
b1100 :
#90
0'
1%
0&
1.
b1001 0
b1001 -
b1001 5
b1001 4
16
b1101 +
b1101 ,
b1101 3
b1101 :
#100
1#
0(
1%
02
0.
b0 0
b10000 -
b10000 5
b10000 4
06
17
b1111 +
b1111 ,
b1111 3
b1111 :
#110
1$
1&
1'
1(
1)
1.
b1 0
b10001 -
b10001 5
b10001 4
16
b1110 +
b1110 ,
b1110 3
b1110 :
#120
0)
0'
1$
0%
1&
0(
0#
1/
0.
01
b10 0
06
07
b10010 -
b10010 5
b10010 4
18
b1010 +
b1010 ,
b1010 3
b1010 :
#130
0&
1(
1.
b11 0
b10011 -
b10011 5
b10011 4
16
b1011 +
b1011 ,
b1011 3
b1011 :
#140
1)
0$
1'
1&
0(
0/
11
0.
b100 0
b10100 -
b10100 5
b10100 4
06
17
b1001 +
b1001 ,
b1001 3
b1001 :
#150
0)
1.
b101 0
b10101 -
b10101 5
b10101 4
16
b1000 +
b1000 ,
b1000 3
b1000 :
